serpyco/__init__.py
serpyco/decorator.py
serpyco/encoder.cp37-win_amd64.pyd
serpyco/encoder.pxd
serpyco/encoder.pyi
serpyco/encoder.pyx
serpyco/exception.py
serpyco/field.py
serpyco/mixin.py
serpyco/py.typed
serpyco/schema.py
serpyco/serializer.cp37-win_amd64.pyd
serpyco/serializer.pyi
serpyco/serializer.pyx
serpyco/util.py
serpyco/validator.py
serpyco_d7-1.3.16.dist-info/LICENSE
serpyco_d7-1.3.16.dist-info/METADATA
serpyco_d7-1.3.16.dist-info/WHEEL
serpyco_d7-1.3.16.dist-info/top_level.txt
serpyco_d7-1.3.16.dist-info/RECORD
