Metadata-Version: 2.1
Name: serpyco-d7
Version: 1.3.16
Summary: Fast serialization of dataclasses using Cython
Home-page: https://github.com/7ws/serpyco
Author: Sébastien Grignard
Author-email: Sébastien Grignard <pub@amakaze.org>, Patrick Mazulo <mazulo@d7.dev>
License: MIT
Project-URL: Homepage, https://github.com/7ws/serpyco
Project-URL: Bug Tracker, https://github.com/7ws/serpyco/issues
Classifier: Development Status :: 5 - Production/Stable
Classifier: Intended Audience :: Developers
Classifier: License :: OSI Approved :: MIT License
Classifier: Programming Language :: Python :: 3
Classifier: Topic :: Software Development :: Libraries
Requires-Python: >=3.7,<3.12
License-File: LICENSE
Requires-Dist: python-dateutil
Requires-Dist: python-rapidjson>=0.8.0
Requires-Dist: typing-inspect>=0.6.0
Requires-Dist: dataclasses; python_version < "3.7"
Provides-Extra: dev
Requires-Dist: black; extra == "dev"
Requires-Dist: build; extra == "dev"
Requires-Dist: dataslots; extra == "dev"
Requires-Dist: mypy; extra == "dev"
Requires-Dist: pytest; extra == "dev"
Requires-Dist: pytest-benchmark; extra == "dev"
Requires-Dist: ruff; extra == "dev"
Requires-Dist: twine; extra == "dev"
Provides-Extra: build-doc
Requires-Dist: sphinx; extra == "build-doc"
Requires-Dist: sphinx-autodoc-typehints; extra == "build-doc"
Requires-Dist: sphinx-rtd-theme; extra == "build-doc"
Requires-Dist: sphinxcontrib-websupport; extra == "build-doc"
